genderperformr/__init__.py
genderperformr/dataset.py
genderperformr/genderperformr.py
genderperformr/model.py
genderperformr/model_new.py
genderperformr/predict.py
genderperformr/utils.py
genderperformr/data/__init__.py
genderperformr/data/consts.py
genderperformr/data/model.pth.tar
genderperformr/data/model_new.pth.tar
genderperformr-1.2.dist-info/LICENSE.txt
genderperformr-1.2.dist-info/METADATA
genderperformr-1.2.dist-info/WHEEL
genderperformr-1.2.dist-info/top_level.txt
genderperformr-1.2.dist-info/RECORD
