Metadata-Version: 2.1
Name: genderperformr
Version: 1.2
Summary: GenderPerformr
Home-page: https://github.com/zijwang/genderperformr
Author: Zijian Wang and David Jurgens
Author-email: zijwang@stanford.edu
License: UNKNOWN
Platform: UNKNOWN
Requires-Python: >=3.6
Requires-Dist: torch (>=0.4.1)
Requires-Dist: numpy
Requires-Dist: unidecode
